setup.cfg
setup.py
softlayer_messaging/__init__.py
softlayer_messaging/auth.py
softlayer_messaging/client.py
softlayer_messaging/compat.py
softlayer_messaging/constants.py
softlayer_messaging/errors.py
softlayer_messaging/queue.py
softlayer_messaging/resource.py
softlayer_messaging/topic.py
softlayer_messaging.egg-info/PKG-INFO
softlayer_messaging.egg-info/SOURCES.txt
softlayer_messaging.egg-info/dependency_links.txt
softlayer_messaging.egg-info/requires.txt
softlayer_messaging.egg-info/top_level.txt
softlayer_messaging/resources/config.json